meg_utils/__init__.py
meg_utils/_synchronize_meg_utils.py
meg_utils/constants.py
meg_utils/conversion.py
meg_utils/data.py
meg_utils/decoding.py
meg_utils/misc.py
meg_utils/pipeline.py
meg_utils/plotting.py
meg_utils/preprocessing.py
meg_utils/sigproc.py
meg_utils-0.1.0.dist-info/licenses/LICENSE
meg_utils-0.1.0.dist-info/METADATA
meg_utils-0.1.0.dist-info/WHEEL
meg_utils-0.1.0.dist-info/top_level.txt
meg_utils-0.1.0.dist-info/RECORD
