Metadata-Version: 2.4
Name: meg_utils
Version: 0.1.0
Summary: A collection of utility functions for MEG analysis.
Home-page: https://github.com/simon-kern/meg_utils
Author: Simon Kern
Author-email: simon.kern@zi-mannheim.de
Classifier: Programming Language :: Python :: 3
Classifier: License :: OSI Approved :: MIT License
Classifier: Operating System :: OS Independent
Requires-Python: >=3.6
License-File: LICENSE
Requires-Dist: autoreject
Requires-Dist: joblib
Requires-Dist: matplotlib
Requires-Dist: mne
Requires-Dist: natsort
Requires-Dist: numpy
Requires-Dist: pandas
Requires-Dist: pyEDFlib
Requires-Dist: scikit_learn
Requires-Dist: scipy
Requires-Dist: seaborn
Requires-Dist: tqdm
Dynamic: author
Dynamic: author-email
Dynamic: classifier
Dynamic: description
Dynamic: description-content-type
Dynamic: home-page
Dynamic: license-file
Dynamic: requires-dist
Dynamic: requires-python
Dynamic: summary
